gofit.cpython-312-darwin.so
gofit-1.0.0.dist-info/RECORD
gofit-1.0.0.dist-info/WHEEL
gofit-1.0.0.dist-info/top_level.txt
gofit-1.0.0.dist-info/METADATA
gofit-1.0.0.dist-info/licenses/LICENSE
