Metadata-Version: 2.4
Name: gofit
Version: 1.0.0
Summary: GOFit: Global Optimization for Fitting problems
Home-page: https://github.com/ralna/gofit
Download-URL: https://github.com/ralna/gofit/releases/
Author: Jaroslav Fowkes
Author-email: jaroslav.fowkes@stfc.ac.uk
License: New BSD
Project-URL: Bug Tracker, https://github.com/ralna/gofit/issues/
Project-URL: Documentation, https://ralna.github.io/GOFit/
Project-URL: Source Code, https://github.com/ralna/gofit/
Keywords: mathematics optimization
Classifier: Development Status :: 5 - Production/Stable
Classifier: Environment :: Console
Classifier: Framework :: IPython
Classifier: Framework :: Jupyter
Classifier: Intended Audience :: Science/Research
Classifier: License :: OSI Approved :: BSD License
Classifier: Operating System :: Unix
Classifier: Programming Language :: Python
Classifier: Programming Language :: Python :: 3
Classifier: Topic :: Scientific/Engineering
Classifier: Topic :: Scientific/Engineering :: Mathematics
Requires-Python: >=3.6
License-File: LICENSE
Requires-Dist: pybind11[global]
Dynamic: author
Dynamic: author-email
Dynamic: classifier
Dynamic: description
Dynamic: description-content-type
Dynamic: download-url
Dynamic: home-page
Dynamic: keywords
Dynamic: license
Dynamic: license-file
Dynamic: project-url
Dynamic: requires-dist
Dynamic: requires-python
Dynamic: summary
